[
	{
		"title": "Google icons",
		"link": "https://fonts.google.com/icons",
		"img": "./images/icons/google.webp",
		"description": "Over 2,500 glyphs in a single font file with a wide range of design variants. ",
		"licence": "Apache License Version 2.0",
		"licencelink": "https://www.apache.org/licenses/LICENSE-2.0.html"
	},
	{
		"title": "css.gg",
		"link": "https://css.gg/",
		"img": "https://css.gg/fav/og2.png",
		"description": "Open-source CSS, SVG and Figma UI Icons, Available in SVG Sprite, styled-components, NPM & API",
		"licence": "MIT",
		"licencelink": "https://css.gg/doc/licence"
	},
	{
		"title": "Feather icons",
		"link": "https://feathericons.com/",
		"img": "./images/icons/feather.webp",
		"description": "Simply beautiful open source icons",
		"licence": "MIT",
		"licencelink": "https://github.com/feathericons/feather/blob/master/LICENSE"
	},
	{
		"title": "SVGrepo",
		"link": "https://www.svgrepo.com",
		"img": "https://www.svgrepo.com/social.png",
		"description": "500.000+ Open-licensed SVG Vector and Icons",
		"licence": "Multiple licenses (SVG Repo License, CC0, MIT...)",
		"licencelink": "https://www.svgrepo.com/page/licensing"
	},
	{
		"title": "Iconmonstr",
		"link": "https://iconmonstr.com",
		"img": "./images/icons/iconmonstr.webp",
		"description": "Free simple icons for your next project",
		"licence": "\"Licensee may use the Work in non-commercial and commercial projects, services or products without attribution.\"",
		"licencelink": "https://iconmonstr.com/license/"
	},
	{
		"title": "Keyicons",
		"link": "https://keyicons.com",
		"img": "./images/icons/keyicons.webp",
		"description": "The clean icon set you were looking for, ready to use in web, mobile development and wherever you want.",
		"licence": "CC BY 4.0",
		"licencelink": "https://keyicons.com"
	},
	{
		"title": "Zwicon",
		"link": "http://zwicon.com",
		"img": "./images/icons/zwicon.webp",
		"description": "The zwicon icon library was made to support our work @zwoelf. Now it is available for free for download.",
		"licence": "CC BY-ND 4.0",
		"licencelink": "http://zwicon.com/how-to-use.html"
	}
]
